tree_sitter_kotlin-1.0.1.dist-info/RECORD
tree_sitter_kotlin-1.0.1.dist-info/WHEEL
tree_sitter_kotlin-1.0.1.dist-info/LICENSE
tree_sitter_kotlin-1.0.1.dist-info/top_level.txt
tree_sitter_kotlin-1.0.1.dist-info/METADATA
tree_sitter_kotlin/binding.c
tree_sitter_kotlin/__init__.pyi
tree_sitter_kotlin/py.typed
tree_sitter_kotlin/_binding.abi3.so
tree_sitter_kotlin/__init__.py
