Metadata-Version: 2.1
Name: tree-sitter-kotlin
Version: 1.0.1
Summary: Kotlin grammar for tree-sitter
Author-email: Amaan Qureshi <amaanq12@gmail.com>
License: MIT
Project-URL: Homepage, https://github.com/tree-sitter-grammars/tree-sitter-kotlin
Keywords: incremental,parsing,tree-sitter,kotlin
Classifier: Intended Audience :: Developers
Classifier: License :: OSI Approved :: MIT License
Classifier: Topic :: Software Development :: Compilers
Classifier: Topic :: Text Processing :: Linguistic
Classifier: Typing :: Typed
Requires-Python: >=3.8
License-File: LICENSE
Provides-Extra: core
Requires-Dist: tree-sitter~=0.21; extra == "core"
